fabric_bearychat.py
setup.py
fabric_bearychat.egg-info/PKG-INFO
fabric_bearychat.egg-info/SOURCES.txt
fabric_bearychat.egg-info/dependency_links.txt
fabric_bearychat.egg-info/not-zip-safe
fabric_bearychat.egg-info/pbr.json
fabric_bearychat.egg-info/requires.txt
fabric_bearychat.egg-info/top_level.txt