Metadata-Version: 1.1
Name: fabric-bearychat
Version: 0.0.2
Summary: Fabric task aided with bearychat.
Home-page: https://github.com/bcho/fabric-bearychat
Author: hbc
Author-email: bcxxxxxx@gmail.com
License: MIT
Platform: UNKNOWN
Classifier: Intended Audience :: Developers
Classifier: Intended Audience :: System Administrators
Classifier: Operating System :: OS Independent
Classifier: Topic :: Software Development
Classifier: Programming Language :: Python :: 2.7
